filesizelib/__init__.py
filesizelib/platform_storage.py
filesizelib/storage.py
filesizelib/storage_unit.py
filesizelib-0.12.1.dist-info/METADATA
filesizelib-0.12.1.dist-info/WHEEL
filesizelib-0.12.1.dist-info/licenses/LICENSE
filesizelib-0.12.1.dist-info/RECORD
